pysearchlight/__init__.py
pysearchlight/examples.py
pysearchlight/sl.py
pysearchlight-1.0.1.dist-info/LICENSE.txt
pysearchlight-1.0.1.dist-info/METADATA
pysearchlight-1.0.1.dist-info/WHEEL
pysearchlight-1.0.1.dist-info/top_level.txt
pysearchlight-1.0.1.dist-info/RECORD
