Metadata-Version: 2.1
Name: pysearchlight
Version: 1.0.1
Summary: A simple and customizable implementation of the searchlight analysis method.
Home-page: https://github.com/andropar/pysearchlight
Author: Johannes Roth
Author-email: Johannes Roth <johannes@roth24.de>
Classifier: Programming Language :: Python :: 3
Classifier: License :: OSI Approved :: MIT License
Classifier: Operating System :: OS Independent
Requires-Python: >=3.7, <4
License-File: LICENSE.txt
